MANIFEST.in
README.txt
setup.cfg
setup.py
wwp/__init__.py
wwp.twitter.egg-info/PKG-INFO
wwp.twitter.egg-info/SOURCES.txt
wwp.twitter.egg-info/dependency_links.txt
wwp.twitter.egg-info/entry_points.txt
wwp.twitter.egg-info/namespace_packages.txt
wwp.twitter.egg-info/not-zip-safe
wwp.twitter.egg-info/paster_plugins.txt
wwp.twitter.egg-info/requires.txt
wwp.twitter.egg-info/top_level.txt
wwp/twitter/README.txt
wwp/twitter/__init__.py
wwp/twitter/config.py
wwp/twitter/configure.zcml
wwp/twitter/configure.zcml~
wwp/twitter/form.py
wwp/twitter/browser/__init__.py
wwp/twitter/browser/addtweet.py
wwp/twitter/browser/configure.zcml
wwp/twitter/browser/feedparser.py
wwp/twitter/browser/find_urls.py
wwp/twitter/browser/twitrssview.pt
wwp/twitter/browser/twitrssview.py
wwp/twitter/browser/twitscheduleview.pt
wwp/twitter/browser/twitscheduleview.py
wwp/twitter/browser/twitterpageview.pt
wwp/twitter/browser/twitterpageview.py
wwp/twitter/browser/twittertrendsview.pt
wwp/twitter/browser/twittertrendsview.py
wwp/twitter/browser/updatetrendsview.pt
wwp/twitter/browser/updatetrendsview.py
wwp/twitter/browser/updatetweetview.pt
wwp/twitter/browser/updatetweetview.py
wwp/twitter/content/__init__.py
wwp/twitter/content/configure.zcml
wwp/twitter/content/twitrss.py
wwp/twitter/content/twitschedule.py
wwp/twitter/content/twitterpage.py
wwp/twitter/content/twittertrends.py
wwp/twitter/interfaces/__init__.py
wwp/twitter/interfaces/twitrss.py
wwp/twitter/interfaces/twitschedule.py
wwp/twitter/interfaces/twitterpage.py
wwp/twitter/interfaces/twittertrends.py
wwp/twitter/portlets/__init__.py
wwp/twitter/portlets/configure.zcml
wwp/twitter/portlets/wwp_twitter_portlet.pt
wwp/twitter/portlets/wwp_twitter_portlet.py
wwp/twitter/profiles/default/factorytool.xml
wwp/twitter/profiles/default/metadata.xml
wwp/twitter/profiles/default/portlets.xml
wwp/twitter/profiles/default/portlets.xml~
wwp/twitter/profiles/default/rolemap.xml
wwp/twitter/profiles/default/types.xml
wwp/twitter/profiles/default/types/TwitterPage.xml
wwp/twitter/profiles/default/types/twitrss.xml
wwp/twitter/profiles/default/types/twitschedule.xml
wwp/twitter/profiles/default/types/twittertrends.xml
wwp/twitter/tests/__init__.py
wwp/twitter/tests/base.py
wwp/twitter/tests/base_twitterportlet.py
wwp/twitter/tests/test_doctest.py
