Metadata-Version: 1.0
Name: wwp.twitter
Version: 1.5.3dev
Summary: UNKNOWN
Home-page: http://svn.plone.org/svn/plone/plone.example
Author: Cannon Scientific
Author-email: pdyson@cannonscientific.com
License: GPL
Keywords: plone twitter
Platform: UNKNOWN
Classifier: Framework :: Plone
Classifier: Intended Audience :: Developers
Classifier: Topic :: Software Development :: Libraries :: Python Modules
Classifier: License :: OSI Approved :: GNU General Public License (GPL)
